gfdlnb/notebooks/ocean/AAIW_PV.ipynb
gfdlnb/notebooks/ocean/ArcticMeanTempSalinity.ipynb
gfdlnb/notebooks/ocean/Bottom_property_bias_WOA18.ipynb
gfdlnb/notebooks/ocean/Drake_Transport.ipynb
gfdlnb/notebooks/ocean/ENSO_variability.ipynb
gfdlnb/notebooks/ocean/Global_Meridional_Overturning.ipynb
gfdlnb/notebooks/ocean/Med_Outflow.ipynb
gfdlnb/notebooks/ocean/Mixed_Layer_Depths.ipynb
gfdlnb/notebooks/ocean/Northward_Heat_Transport.ipynb
gfdlnb/notebooks/ocean/Overturning_zrho.ipynb
gfdlnb/notebooks/ocean/SST_bias_NOAA_OISSTv2.ipynb
gfdlnb/notebooks/ocean/Test_Notebook.ipynb
gfdlnb/notebooks/ocean/Tidal_Energy_Conversion_Deep.ipynb
gfdlnb/notebooks/ocean/WMT_North_Atlantic.ipynb
gfdlnb/notebooks/ocean/WOA13_yz_bias.ipynb
gfdlnb/notebooks/ocean/WOA18_yz_bias.ipynb
gfdlnb/notebooks/ocean/experiment_intercomparison.ipynb
gfdlnb/notebooks/ocean/ssh_wbc.ipynb
gfdlnb/resources/config.yaml
gfdlnb/tools/VerticalSplitScale.py
gfdlnb/tools/custom_preprocessor.py
gfdlnb/tools/om4common.py
gfdlnb/tools/update_notebook_config.py
gfdlnb-0.0.4.data/scripts/gfdl-notebooks
gfdlnb-0.0.4.dist-info/LICENSE.txt
gfdlnb-0.0.4.dist-info/METADATA
gfdlnb-0.0.4.dist-info/WHEEL
gfdlnb-0.0.4.dist-info/top_level.txt
gfdlnb-0.0.4.dist-info/RECORD
