Metadata-Version: 2.1
Name: gfdlnb
Version: 0.0.4
Summary: GFDL Model Analysis Notebooks
Author-email: John Krasting <john.krasting@noaa.gov>
License: Software code created by U.S. Government employees is not subject to copyright
Project-URL: homepage, https://github.com/jkrasting/mar
Project-URL: documentation, https://gfdl-notebooks.readthedocs.io
Project-URL: repository, https://github.com/jkrasting/mar
Keywords: climate modeling,gfdl
Classifier: Development Status :: 3 - Alpha
Classifier: Intended Audience :: Science/Research
Classifier: Topic :: Scientific/Engineering
Classifier: License :: Public Domain
Classifier: Programming Language :: Python :: 3.8
Classifier: Programming Language :: Python :: 3.9
Requires-Python: >=3.11
License-File: LICENSE.txt
Requires-Dist: importlib-metadata<5.0.0
Requires-Dist: numpy>=1.21.0
Requires-Dist: xarray>=0.20.0
Provides-Extra: test
Requires-Dist: pytest; extra == "test"
